halfadder.v
// A module that implements sum of two numbers
module HA(A,B,sum,carry);
input A,B;
output sum,carry;
wire A,B,sum,carry;
assign sum=A^B;
assign carry=A&B;
endmodule

fulladder.v
// A module that implements full Adder circuit of two four-bit numbers
module FA(A,B,C_prev,S,C_next);
input A,B,C_prev;
output S,C_next;
wire A,B,C_prev,s,c_next,tmpC,tmpS;
HA HA1(.A(A),.B(B),.sum(tmpS),.carry(tmpC));
HA HA2(.A(tmpS),.B(C_prev),.sum(S),.carry(tmpC));
assign C_next=(A&B)|(tmpS&C_prev);
endmodule

fa_tb.v
// Test bench for full Adder;
module fa_test();
reg A=0,B=0,C=0;
wire exptS,exptC,opS,opC;
assign exptS=((A^B)^C);
assign exptC=(A&B)+((A^B)&C);
initial begin
$dumpfile("FAdump.vcd");
$dumpvars(0,fa_test);
#2;
A=0;B=0;C=0;
#2;
A=0;B=0;C=1;
#2;
A=0;B=1;C=0;
#2;
A=0;B=1;C=1;
#2;
A=1;B=0;C=0;
#2;
A=1;B=0;C=1;
#2;
A=1;B=1;C=0;
#2;
A=1;B=1;C=1;
#8;
end
FA test(A,B,C,opS,opC);
endmodule

FAdump.vcd
$date
	Sun Aug  5 08:39:18 2018
$end
$version
	Icarus Verilog
$end
$timescale
	1s
$end
$scope module fa_test $end
$var wire 1 ! exptS $end
$var wire 1 " opS $end
$var wire 1 # opC $end
$var wire 1 $ exptC $end
$var reg 1 % A $end
$var reg 1 & B $end
$var reg 1 ' C $end
$scope module test $end
$var wire 1 % A $end
$var wire 1 & B $end
$var wire 1 # C_next $end
$var wire 1 ' C_prev $end
$var wire 1 ( tmpC $end
$var wire 1 ) tmpS $end
$var wire 1 " S $end
$scope module HA1 $end
$var wire 1 % A $end
$var wire 1 & B $end
$var wire 1 ( carry $end
$var wire 1 ) sum $end
$upscope $end
$scope module HA2 $end
$var wire 1 ) A $end
$var wire 1 ' B $end
$var wire 1 ( carry $end
$var wire 1 " sum $end
$upscope $end
$upscope $end
$upscope $end
$enddefinitions $end
#0
$dumpvars
0)
0(
0'
0&
0%
0$
0#
0"
0!
$end
#4
1"
1!
1'
#6
1)
0'
1&
#8
1#
0"
x(
1$
0!
1'
#10
0#
1"
0(
0$
1!
0'
0&
1%
#12
1#
0"
x(
1$
0!
1'
#14
0)
x(
1$
0'
1&
#16
1"
1!
1'
